{
  "context": "client",
  "identifier": "com.pa.quitch.tfcl",
  "display_name": "Time From Commander Landing",
  "description": "Restarts the in-game clock and chronocam display from 0 when the Commander lands.",
  "author": "Quitch",
  "version": "1.0.0",
  "build": "116982",
  "date": "2024-03-26",
  "signature": " ",
  "forum": "https://steamcommunity.com/app/386070/discussions/0/4291440749285806358/",
  "icon": "https://raw.githubusercontent.com/Quitch/Time-From-Commander-Landing/develop/images/icon.png",
  "category": ["ui", "classic", "titans"],
  "priority": 100,
  "scenes": {
    "live_game": ["coui://ui/mods/com.pa.quitch.tfcl/live_game/game_state.js"],
    "live_game_options_bar": [
      "coui://ui/mods/com.pa.quitch.tfcl/live_game_options_bar/timer.js"
    ],
    "live_game_time_bar": [
      "coui://ui/mods/com.pa.quitch.tfcl/live_game_time_bar/timer.js"
    ]
  },
  "github": "https://github.com/Quitch/Time-From-Commander-Landing"
}
